[
 {
  "name": "Adilon ",
  "pname": "Burim",
  "surname": "Starabanja",
  "gender": "M",
  "class": "X1",
  "teacher": "Arben Ramadani"
 },
 {
  "name": "Alorin",
  "pname": "Florim",
  "surname": "Hajredini",
  "gender": "M",
  "class": "X1",
  "teacher": "Arben Ramadani"
 },
 {
  "name": "Artina",
  "pname": "Nexhat",
  "surname": "Selishta",
  "gender": "F",
  "class": "X1",
  "teacher": "Arben Ramadani"
 },
 {
  "name": "Bleon",
  "pname": "Blerim",
  "surname": "Ferizaj",
  "gender": "M",
  "class": "X1",
  "teacher": "Arben Ramadani"
 },
 {
  "name": "Bleron",
  "pname": "Ibrahim",
  "surname": "Ajvazi",
  "gender": "M",
  "class": "X1",
  "teacher": "Arben Ramadani"
 },
 {
  "name": "Blin",
  "pname": "Driton",
  "surname": "Agushi",
  "gender": "M",
  "class": "X1",
  "teacher": "Arben Ramadani"
 },
 {
  "name": "Donart",
  "pname": "Fitim",
  "surname": "Dauti",
  "gender": "M",
  "class": "X1",
  "teacher": "Arben Ramadani"
 },
 {
  "name": "Egzon",
  "pname": "Ramadan",
  "surname": "Spahiu",
  "gender": "M",
  "class": "X1",
  "teacher": "Arben Ramadani"
 },
 {
  "name": "Emir",
  "pname": "Ragip",
  "surname": "Hyseni",
  "gender": "M",
  "class": "X1",
  "teacher": "Arben Ramadani"
 },
 {
  "name": "Erblin",
  "pname": "Samet",
  "surname": "Dermaku",
  "gender": "M",
  "class": "X1",
  "teacher": "Arben Ramadani"
 },
 {
  "name": "Erion",
  "pname": "Halim",
  "surname": "Mehmeti",
  "gender": "M",
  "class": "X1",
  "teacher": "Arben Ramadani"
 },
 {
  "name": "Erlind",
  "pname": "Vaxhid",
  "surname": "Zymberi",
  "gender": "M",
  "class": "X1",
  "teacher": "Arben Ramadani"
 },
 {
  "name": "Eron ",
  "pname": "Naser",
  "surname": "Ibrahimi",
  "gender": "M",
  "class": "X1",
  "teacher": "Arben Ramadani"
 },
 {
  "name": "Korab ",
  "pname": "Musli",
  "surname": "Arifi",
  "gender": "M",
  "class": "X1",
  "teacher": "Arben Ramadani"
 },
 {
  "name": "Leart",
  "pname": "Nexhmedin",
  "surname": "Asani",
  "gender": "M",
  "class": "X1",
  "teacher": "Arben Ramadani"
 },
 {
  "name": "Leon ",
  "pname": "Skender",
  "surname": "Klaiqi",
  "gender": "M",
  "class": "X1",
  "teacher": "Arben Ramadani"
 },
 {
  "name": "Lijana",
  "pname": "Ridvan",
  "surname": "Ahmeti",
  "gender": "F",
  "class": "X1",
  "teacher": "Arben Ramadani"
 },
 {
  "name": "Lorik ",
  "pname": "Naim",
  "surname": "Rama",
  "gender": "M",
  "class": "X1",
  "teacher": "Arben Ramadani"
 },
 {
  "name": "Megi",
  "pname": "Ylberi",
  "surname": "Rushiti",
  "gender": "F",
  "class": "X1",
  "teacher": "Arben Ramadani"
 },
 {
  "name": "Nazmi",
  "pname": "Fitim",
  "surname": "Jonuzi",
  "gender": "M",
  "class": "X2",
  "teacher": "Arben Ramadani"
 },
 {
  "name": "Olti ",
  "pname": "Berat",
  "surname": "Ferati",
  "gender": "M",
  "class": "X1",
  "teacher": "Arben Ramadani"
 },
 {
  "name": "Rijon",
  "pname": "Besnik",
  "surname": "Shabani",
  "gender": "M",
  "class": "X1",
  "teacher": "Arben Ramadani"
 },
 {
  "name": "Roland",
  "pname": "Sherif",
  "surname": "Sherifi",
  "gender": "M",
  "class": "X1",
  "teacher": "Arben Ramadani"
 },
 {
  "name": "Viola",
  "pname": "Skender",
  "surname": "Demiri",
  "gender": "F",
  "class": "X1",
  "teacher": "Arben Ramadani"
 },
 {
  "name": "Yll",
  "pname": "Faik",
  "surname": "Ibrahimi",
  "gender": "M",
  "class": "X1",
  "teacher": "Arben Ramadani"
 },
 {
  "name": "Shaban",
  "pname": "Asllan",
  "surname": "Bajrami",
  "gender": "M",
  "class": "X1",
  "teacher": "Arben Ramadani"
 },
 {
  "name": "Ibrahim ",
  "pname": "Sadullah",
  "surname": "Ibrahimi",
  "gender": "M",
  "class": "X1",
  "teacher": "Arben Ramadani"
 },
 {
  "name": "Arti",
  "surname": "Uka",
  "class": "X1",
  "teacher": "Arben Ramadani"
 },
 {
  "name": "Alejna",
  "pname": "Burim",
  "surname": "Haliti",
  "gender": "F",
  "class": "X2.",
  "teacher": "Florida Dermaku"
 },
 {
  "name": "Andi",
  "pname": "Adnan",
  "surname": "Syla",
  "gender": "M",
  "class": "X2",
  "teacher": "Florida Dermaku"
 },
 {
  "name": "Aron",
  "pname": "Mejdi",
  "surname": "Ahmeti",
  "gender": "M",
  "class": "X2",
  "teacher": "Florida Dermaku"
 },
 {
  "name": "Bardhosh",
  "pname": "Qerim",
  "surname": "Lenjani",
  "gender": "M",
  "class": "X2",
  "teacher": "Florida Dermaku"
 },
 {
  "name": "Denis",
  "pname": "Murtez",
  "surname": "Kqiku",
  "gender": "M",
  "class": "X2",
  "teacher": "Florida Dermaku"
 },
 {
  "name": "Elda",
  "pname": "Florim",
  "surname": "Ramadani",
  "gender": "F",
  "class": "X2",
  "teacher": "Florida Dermaku"
 },
 {
  "name": "Erblin",
  "pname": "Bashkim",
  "surname": "Fazliu",
  "gender": "M",
  "class": "X2",
  "teacher": "Florida Dermaku"
 },
 {
  "name": "Eriol",
  "pname": "Milaim",
  "surname": "Avdili",
  "gender": "M",
  "class": "X2",
  "teacher": "Florida Dermaku"
 },
 {
  "name": "Erton",
  "pname": "Bashkim",
  "surname": "Islami",
  "gender": "M",
  "class": "X2",
  "teacher": "Florida Dermaku"
 },
 {
  "name": "Ermal",
  "pname": "Elvis",
  "surname": "Hasani",
  "class": "X2",
  "teacher": "Florida Dermaku"
 },
 {
  "name": "Fidan ",
  "pname": "Mehmet",
  "surname": "Ramushi",
  "gender": "M",
  "class": "X2",
  "teacher": "Florida Dermaku"
 },
 {
  "name": "Fllad",
  "pname": "Vllaznim",
  "surname": "Qerimi",
  "gender": "M",
  "class": "X2",
  "teacher": "Florida Dermaku"
 },
 {
  "name": "Gers",
  "pname": "Bekim",
  "surname": "Islami",
  "gender": "M",
  "class": "X2",
  "teacher": "Florida Dermaku"
 },
 {
  "name": "Gjergj",
  "pname": "Bejto",
  "surname": "Latifaj",
  "gender": "M",
  "class": "X2",
  "teacher": "Florida Dermaku"
 },
 {
  "name": "Leonrad",
  "pname": "Avdi",
  "surname": "Jerliu",
  "gender": "M",
  "class": "X2",
  "teacher": "Florida Dermaku"
 },
 {
  "name": "Luan",
  "pname": "Asllan",
  "surname": "Shkodra",
  "gender": "M",
  "class": "X2",
  "teacher": "Florida Dermaku"
 },
 {
  "name": "Milot",
  "pname": "Driton",
  "surname": "Maliqi",
  "gender": "M",
  "class": "X2",
  "teacher": "Florida Dermaku"
 },
 {
  "name": "Omer",
  "pname": "Alishukri",
  "surname": "Azemi",
  "gender": "M",
  "class": "X2",
  "teacher": "Florida Dermaku"
 },
 {
  "name": "Olti ",
  "pname": "Ridvan",
  "surname": "Ibrahimi",
  "gender": "M",
  "class": "X2",
  "teacher": "Florida Dermaku"
 },
 {
  "name": "Rajlinda",
  "pname": "Muhamet",
  "surname": "Hafizi",
  "gender": "F",
  "class": "X2",
  "teacher": "Florida Dermaku"
 },
 {
  "name": "Rijon",
  "pname": "Selman",
  "surname": "Jerliu",
  "gender": "M",
  "class": "X2",
  "teacher": "Florida Dermaku"
 },
 {
  "name": "Rinor",
  "pname": "Bastri",
  "surname": "Avdyli",
  "gender": "M",
  "class": "X2",
  "teacher": "Florida Dermaku"
 },
 {
  "name": "Rinor",
  "pname": "Rexhep",
  "surname": "Dauti",
  "gender": "M",
  "class": "X2",
  "teacher": "Florida Dermaku"
 },
 {
  "name": "Artina",
  "pname": "Bashkim",
  "surname": "Qerimi",
  "gender": "F",
  "class": "X\/3",
  "teacher": "Gojarta Neziri"
 },
 {
  "name": "Alketa",
  "pname": "Arben",
  "surname": "Vranovci",
  "gender": "F",
  "class": "X\/3",
  "teacher": "Gojarta Neziri"
 },
 {
  "name": "ERDI",
  "pname": "Fidan",
  "surname": "KASTRATI",
  "class": "X\/3",
  "teacher": "Gojarta Neziri"
 },
 {
  "name": "RILAND",
  "pname": "Skender",
  "surname": "PIREVA",
  "class": "X\/3",
  "teacher": "Gojarta Neziri"
 },
 {
  "name": "QËNDRIM",
  "pname": "Bajram",
  "surname": "BAJRA",
  "gender": "M",
  "class": "X\/3",
  "teacher": "Gojarta Neziri"
 },
 {
  "name": "RAMUSH",
  "pname": "Zjadin",
  "surname": "MAROVCA",
  "gender": "M",
  "class": "X\/3",
  "teacher": "Gojarta Neziri"
 },
 {
  "name": "ARBAS",
  "pname": "Aziz",
  "surname": "MURTEZI",
  "gender": "M",
  "class": "X\/3",
  "teacher": "Gojarta Neziri"
 },
 {
  "name": "ARTOR",
  "pname": "Xherlil",
  "surname": "MALOKU",
  "gender": "M",
  "class": "X\/3",
  "teacher": "Gojarta Neziri"
 },
 {
  "name": "ENDRIT",
  "pname": "avdyl",
  "surname": "BLLACA",
  "gender": "M",
  "class": "X\/3",
  "teacher": "Gojarta Neziri"
 },
 {
  "name": "OMAR",
  "pname": "Parim",
  "surname": "HOXHA",
  "gender": "M",
  "class": "X\/3",
  "teacher": "Gojarta Neziri"
 },
 {
  "name": "DRILON",
  "pname": "Adnan",
  "surname": "XHELADINI",
  "gender": "M",
  "class": "X\/3",
  "teacher": "Gojarta Neziri"
 },
 {
  "name": "Erdi",
  "pname": "Perparim",
  "surname": "Murati",
  "gender": "M",
  "class": "X\/3",
  "teacher": "Gojarta Neziri"
 },
 {
  "name": "URIM",
  "pname": "Lirim",
  "surname": "BAJRAMI",
  "gender": "M",
  "class": "X\/3",
  "teacher": "Gojarta Neziri"
 },
 {
  "name": "ARIDON",
  "pname": "Murat",
  "surname": "BAJRAMI",
  "gender": "M",
  "class": "X\/3",
  "teacher": "Gojarta Neziri"
 },
 {
  "name": "ERJON",
  "pname": "Gezim",
  "surname": "RAMIZI",
  "gender": "M",
  "class": "X\/3",
  "teacher": "Gojarta Neziri"
 },
 {
  "name": "DARDAN",
  "pname": "Limon",
  "surname": "BERISHA",
  "gender": "M",
  "class": "X\/3",
  "teacher": "Gojarta Neziri"
 },
 {
  "name": "Artinian",
  "pname": "Fisnik",
  "surname": "OSMANI",
  "gender": "F",
  "class": "X\/3",
  "teacher": "Gojarta Neziri"
 },
 {
  "name": "ERVIN",
  "pname": "Fidan",
  "surname": "KALLABA",
  "gender": "M",
  "class": "X\/3",
  "teacher": "Gojarta Neziri"
 },
 {
  "name": "ALBAN",
  "pname": "Afrim",
  "surname": "VELIU",
  "class": "X\/3",
  "teacher": "Gojarta Neziri"
 },
 {
  "name": "Rijon",
  "pname": "Naser",
  "surname": "Ibrahimi",
  "gender": "M",
  "class": "x\/3",
  "teacher": "Gojarta Neziri"
 },
 {
  "name": "YLL",
  "pname": "Besim ",
  "surname": "SHABANI",
  "class": "X\/3",
  "teacher": "Gojarta Neziri"
 },
 {
  "name": "Leart",
  "pname": "Selajdin",
  "surname": "Avdyli",
  "gender": "M",
  "class": "X\/3",
  "teacher": "Gojarta Neziri"
 },
 {
  "name": "RENIS",
  "surname": "ABAZI",
  "class": "X\/3"
 },
 {
  "name": "ENDRIT",
  "pname": "Abedin",
  "surname": "DEMIRI",
  "gender": "M",
  "class": "X\/3",
  "teacher": "Gojarta Neziri"
 },
 {
  "name": "ALBION",
  "pname": "Kadri",
  "surname": "MUSTAFA",
  "gender": "M",
  "class": "X\/4",
  "teacher": "Naser Behluli"
 },
 {
  "name": "ARLIND",
  "pname": "Hysen",
  "surname": "ZAHIRI",
  "gender": "M",
  "class": "X\/4",
  "teacher": "Naser Behluli"
 },
 {
  "name": "BAKI",
  "pname": "Ramadan",
  "surname": "RAHIMI",
  "gender": "M",
  "class": "X\/4",
  "teacher": "Naser Behluli"
 },
 {
  "name": "ETIJON",
  "pname": "Astrit",
  "surname": "SAHITI",
  "gender": "M",
  "class": "X\/4",
  "teacher": "Naser Behluli"
 },
 {
  "name": "LEONARD",
  "pname": "Arben",
  "surname": "KAJTAZI",
  "gender": "M",
  "class": "X\/4",
  "teacher": "Naser Behluli"
 },
 {
  "name": "DEMIR",
  "pname": "Fadil",
  "surname": "REXHEPI",
  "gender": "M",
  "class": "X\/4",
  "teacher": "Naser Behluli"
 },
 {
  "name": "ELION",
  "pname": "Naser",
  "surname": "HYSENI",
  "gender": "M",
  "class": "X\/4",
  "teacher": "Naser Behluli"
 },
 {
  "name": "EDUARD",
  "pname": "Skender",
  "surname": "JAHIRI",
  "gender": "M",
  "class": "X\/4",
  "teacher": "Naser Behluli"
 },
 {
  "name": "EDI",
  "pname": "Runit",
  "surname": "ZEJNULLAHU",
  "gender": "M",
  "class": "X\/4",
  "teacher": "Naser Behluli"
 },
 {
  "name": "DIELLON",
  "pname": "Fitim",
  "surname": "LIMANI",
  "gender": "M",
  "class": "X\/4",
  "teacher": "Naser Behluli"
 },
 {
  "name": "DONAT",
  "pname": "Bislim",
  "surname": "ISMAILI",
  "gender": "M",
  "class": "X\/4",
  "teacher": "Naser Behluli"
 },
 {
  "name": "ENDRIT",
  "pname": "Selman",
  "surname": "BAJRAMI",
  "gender": "M",
  "class": "X\/4",
  "teacher": "Naser Behluli"
 },
 {
  "name": "OMER",
  "pname": "Blerim",
  "surname": "TAHIRI",
  "gender": "M",
  "class": "X\/4",
  "teacher": "Naser Behluli"
 },
 {
  "name": "SADULLA",
  "pname": "Rexhep",
  "surname": "FETAHU",
  "gender": "M",
  "class": "X\/4",
  "teacher": "Naser Behluli"
 },
 {
  "name": "VEGIM",
  "pname": "Vegim",
  "surname": "ZAHIRI",
  "gender": "M",
  "class": "X\/4",
  "teacher": "Naser Behluli"
 },
 {
  "name": "ELONIT",
  "pname": "Islam",
  "surname": "HAJREDINI",
  "gender": "M",
  "class": "X\/4",
  "teacher": "Naser Behluli"
 },
 {
  "name": "ARIANIT",
  "pname": "Pjeter",
  "surname": "GASHI",
  "gender": "M",
  "class": "X5",
  "teacher": "Sali Halili"
 },
 {
  "name": "ALBAN",
  "pname": "Bexhet",
  "surname": "RAMADANI",
  "gender": "M",
  "class": "X5",
  "teacher": "Sali Halili"
 },
 {
  "name": "BESNIK",
  "pname": "SHPETIM",
  "surname": "MORINA",
  "gender": "M",
  "class": "X5",
  "teacher": "Sali Halili"
 },
 {
  "name": "EDON",
  "pname": "SHABAN",
  "surname": "ZUZAKU",
  "gender": "M",
  "class": "X5",
  "teacher": "Sali Halili"
 },
 {
  "name": "ERDI",
  "pname": "ENVER",
  "surname": "MUSA",
  "gender": "M",
  "class": "X5",
  "teacher": "Sali Halili"
 },
 {
  "name": "ERVIN",
  "pname": "BURIM",
  "surname": "ISENI",
  "gender": "M",
  "class": "X5",
  "teacher": "Sali Halili"
 },
 {
  "name": "ESHREF",
  "pname": "HALIM",
  "surname": "HAZIRI",
  "gender": "M",
  "class": "X5",
  "teacher": "Sali Halili"
 },
 {
  "name": "FATLUM",
  "pname": "FAREDIN",
  "surname": "MEHMETI",
  "gender": "M",
  "class": "X5",
  "teacher": "Sali Halili"
 },
 {
  "name": "RINOR",
  "pname": "BAJRAM",
  "surname": "HALILI",
  "gender": "M",
  "class": "X5",
  "teacher": "Sali Halili"
 },
 {
  "name": "SHPETIM",
  "pname": "NASER",
  "surname": "MORINA",
  "gender": "M",
  "class": "X5",
  "teacher": "Sali Halili"
 },
 {
  "name": "VALDET",
  "pname": "Tahit",
  "surname": "SELMANI",
  "gender": "M",
  "class": "X5",
  "teacher": "Sali Halili"
 },
 {
  "name": "Ardit",
  "pname": "Avni",
  "surname": "NAMONI",
  "gender": "M",
  "class": "X5",
  "teacher": "Sali Halili"
 },
 {
  "name": "ERDIN",
  "pname": "SHAIP",
  "surname": "MUSLIU",
  "gender": "M",
  "class": "X5",
  "teacher": "Sali Halili"
 },
 {
  "name": "ERTON",
  "pname": "AVNI",
  "surname": "TERSTENA",
  "gender": "M",
  "class": "X5",
  "teacher": "Sali Halili"
 },
 {
  "name": "Enis",
  "pname": "Emin",
  "surname": "Sejdiu",
  "gender": "M",
  "class": "X5",
  "teacher": "Sali Halili"
 },
 {
  "name": "Benedik",
  "pname": "Bekim",
  "surname": "Halimi",
  "gender": "M",
  "class": "X5",
  "teacher": "Sali Halili"
 },
 {
  "name": "AGNESA",
  "pname": "FATMIR",
  "surname": "HASHANI",
  "gender": "F",
  "class": "X6",
  "teacher": "Muhamed Salihu"
 },
 {
  "name": "ARTIOLA",
  "pname": "RIFAT ",
  "surname": "SHERIFI",
  "gender": "F",
  "class": "X6",
  "teacher": "Muhamed Salihu"
 },
 {
  "name": "AVDYL",
  "pname": "BARDHYL",
  "surname": "BAJRAMI",
  "gender": "M",
  "class": "X6",
  "teacher": "Muhamed Salihu"
 },
 {
  "name": "DIONIS ",
  "pname": "NEXHAT",
  "surname": "JEKUPI",
  "gender": "M",
  "class": "X6",
  "teacher": "Muhamed Salihu"
 },
 {
  "name": "DONAT",
  "pname": "ELBASAN",
  "surname": "HYSENI",
  "gender": "M",
  "class": "X6",
  "teacher": "Muhamed Salihu"
 },
 {
  "name": "ELMEDINA ",
  "pname": "SELIM ",
  "surname": "JERLIU",
  "gender": "F",
  "class": "X6",
  "teacher": "Muhamed Salihu"
 },
 {
  "name": "ENESA",
  "pname": "FITIM",
  "surname": "MIFTARI",
  "gender": "F",
  "class": "X6",
  "teacher": "Muhamed Salihu"
 },
 {
  "name": "ERHAN",
  "pname": "AVNI",
  "surname": "BISLIMI",
  "gender": "M",
  "class": "X6",
  "teacher": "Muhamed Salihu"
 },
 {
  "name": "ERIN",
  "pname": "BETIM",
  "surname": "YMERI",
  "gender": "F",
  "class": "X6",
  "teacher": "Muhamed Salihu"
 },
 {
  "name": "Engjull",
  "surname": "Bllaca"
 },
 {
  "name": "ERIS",
  "pname": "BLERIM",
  "surname": "MIFTARI",
  "gender": "M",
  "class": "X6",
  "teacher": "Muhamed Salihu"
 },
 {
  "name": "OLTI",
  "pname": "FADIL",
  "surname": "HALITI",
  "gender": "M",
  "class": "X6",
  "teacher": "Muhamed Salihu"
 },
 {
  "name": "OLTJAN",
  "pname": "AGIM",
  "surname": "SELMANI",
  "gender": "M",
  "class": "X6",
  "teacher": "Muhamed Salihu"
 },
 {
  "name": "ORNELA",
  "pname": "FLORIM",
  "surname": "BAJRAMI",
  "gender": "F",
  "class": "X6",
  "teacher": "Muhamed Salihu"
 },
 {
  "name": "SUEJD",
  "pname": "ILIR",
  "surname": "ALIU",
  "gender": "M",
  "class": "X6",
  "teacher": "Muhamed Salihu"
 },
 {
  "name": "TRIUMF",
  "pname": "BESIM ",
  "surname": "CUCI",
  "gender": "M",
  "class": "X6",
  "teacher": "Muhamed Salihu"
 },
 {
  "name": "VANESA",
  "pname": "FATMIR",
  "surname": "HASHANI",
  "gender": "F",
  "class": "X6",
  "teacher": "Muhamed Salihu"
 },
 {
  "name": "VENIS",
  "pname": "KUDRET",
  "surname": "DERMAKU",
  "gender": "M",
  "class": "X6",
  "teacher": "Muhamed Salihu"
 },
 {
  "name": "LORENT",
  "pname": " Selver",
  "surname": "HAFIZI",
  "gender": "M",
  "class": "X7",
  "teacher": "Mexhid Cani"
 },
 {
  "name": "ERION",
  "pname": "Ali",
  "surname": "SHABANI",
  "gender": "M",
  "class": "X7",
  "teacher": "Mexhid Cani"
 },
 {
  "name": "JONUZ",
  "pname": "Rmadan ",
  "surname": "KQIKU",
  "gender": "M",
  "class": "X7",
  "teacher": "Mexhid Cani"
 },
 {
  "name": "ERON",
  "pname": "Hamzi",
  "surname": "HASANI",
  "gender": "M",
  "class": "X7",
  "teacher": "Mexhid Cani"
 },
 {
  "name": "SHPEND",
  "pname": "Fatmir  ",
  "surname": "TAHIRI",
  "gender": "M",
  "class": "X7",
  "teacher": "Mexhid Cani"
 },
 {
  "name": "ADHURIM",
  "pname": "Sabedin",
  "surname": "SALIHU",
  "gender": "M",
  "class": "X7",
  "teacher": "Mexhid Cani"
 },
 {
  "name": "DIARD",
  "pname": " Lumni",
  "surname": "PAJAZITI",
  "gender": "M",
  "class": "X7",
  "teacher": "Mexhid Cani"
 },
 {
  "name": "ERJON",
  "pname": "Sefer ",
  "surname": "RAMADANI",
  "gender": "M",
  "class": "X7",
  "teacher": "Mexhid Cani"
 },
 {
  "name": "ERLON",
  "pname": " Azem",
  "surname": "SHABANI",
  "gender": "M",
  "class": "X7",
  "teacher": "Mexhid Cani"
 },
 {
  "name": "ALBATRIT",
  "pname": " Mejdi",
  "surname": "BEQIRI",
  "gender": "M",
  "class": "X7",
  "teacher": "Mexhid Cani"
 },
 {
  "name": "BARDHYL",
  "pname": " Murat",
  "surname": "TAHIRI",
  "gender": "M",
  "class": "X7",
  "teacher": "Mexhid Cani"
 },
 {
  "name": "FETAH",
  "pname": "Feriz",
  "surname": "HAFIZI",
  "gender": "M",
  "class": "X7",
  "teacher": "Mexhid Cani"
 },
 {
  "name": "ANIT",
  "pname": "Tefik",
  "surname": "SYLEJMANI",
  "gender": "M",
  "class": "X7",
  "teacher": "Mexhid Cani"
 },
 {
  "name": "ISUF",
  "pname": "Rexhep",
  "surname": "KQIKU",
  "gender": "M",
  "class": "X7",
  "teacher": "Mexhid Cani"
 },
 {
  "name": "Fatlind",
  "surname": "Asllani",
  "gender": "M",
  "class": "X\/7",
  "teacher": "Mexhid Cani"
 },
 {
  "name": "Shefket",
  "surname": "Murati",
  "gender": "M",
  "class": "X\/7",
  "teacher": "Mexhid Cani"
 },
 {
  "name": "ALMIR",
  "surname": "ARIFI",
  "class": "X7",
  "teacher": "Mexhid Cani"
 },
 {
  "name": "LEONIS",
  "surname": "BUNJAKU",
  "class": "X7",
  "teacher": "Mexhid Cani"
 },
 {
  "name": "OLTION",
  "surname": "ALIU",
  "gender": "M",
  "class": "X7",
  "teacher": "Mexhid Cani"
 },
 {
  "name": "DIART",
  "pname": " Besnik",
  "surname": "MALIQI",
  "gender": "M",
  "class": "X\/8",
  "teacher": "Fazli Sermaxhaj"
 },
 {
  "name": "ERMAL",
  "surname": "SHEFKIU",
  "class": "X\/8",
  "teacher": "Fazli Sermaxhaj"
 },
 {
  "name": "ERDON",
  "pname": " Xhavit",
  "surname": "ABDULLAHI",
  "gender": "M",
  "class": "X\/8",
  "teacher": "Fazli Sermaxhaj"
 },
 {
  "name": "ELDI",
  "pname": " Feriz",
  "surname": "SEJDIU",
  "gender": "M",
  "class": "X\/8",
  "teacher": "Fazli Sermaxhaj"
 },
 {
  "name": "YLL",
  "pname": " Hajrush",
  "surname": "KRASNIQI",
  "gender": "M",
  "class": "X\/8",
  "teacher": "Fazli Sermaxhaj"
 },
 {
  "name": "FATJON",
  "pname": " Mejdi",
  "surname": "IBRAHIMI",
  "gender": "M",
  "class": "X\/8",
  "teacher": "Fazli Sermaxhaj"
 },
 {
  "name": "ALMEDIN",
  "pname": "Abedin",
  "surname": "BAJRAMI",
  "gender": "M",
  "class": "X\/8",
  "teacher": "Fazli Sermaxhaj"
 },
 {
  "name": "ERMAL",
  "surname": "HAZIRI",
  "class": "X\/8",
  "teacher": "Fazli Sermaxhaj"
 },
 {
  "name": "EDI",
  "pname": "Sahit",
  "surname": "SYLA",
  "gender": "M",
  "class": "X\/8",
  "teacher": "Fazli Sermaxhaj"
 },
 {
  "name": "GETUAR",
  "pname": "Izjadin",
  "surname": "SPAHIU",
  "gender": "M",
  "class": "X\/8",
  "teacher": "Fazli Sermaxhaj"
 },
 {
  "name": "SHYQERI",
  "pname": "Ruzhdi",
  "surname": "KURTESHI",
  "gender": "M",
  "class": "X\/8",
  "teacher": "Fazli Sermaxhaj"
 },
 {
  "name": "ENDRIT ",
  "pname": "Rrustem",
  "surname": "JERLIU",
  "gender": "M",
  "class": "X\/8",
  "teacher": "Fazli Sermaxhaj"
 },
 {
  "name": "ELVIS",
  "pname": "Luan",
  "surname": "MUSTAFA",
  "gender": "M",
  "class": "X\/8",
  "teacher": "Fazli Sermaxhaj"
 },
 {
  "name": "ERBLIND",
  "pname": "Gazmend",
  "surname": "SPAHIU",
  "gender": "M",
  "class": "X\/8",
  "teacher": "Fazli Sermaxhaj"
 },
 {
  "name": "ALBERT",
  "pname": "Gazmend",
  "surname": "SPAHIU",
  "gender": "M",
  "class": "X\/8",
  "teacher": "Fazli Sermaxhaj"
 },
 {
  "name": "Halis",
  "pname": "Nazmi",
  "surname": "Aasllani",
  "gender": "M",
  "class": "X\/8",
  "teacher": "Fazli Sermaxhaj"
 },
 {
  "name": "ALBION",
  "pname": "SHEFKET",
  "surname": "MUSLIU",
  "gender": "M",
  "class": "X9",
  "teacher": "Agim Tahiri"
 },
 {
  "name": "ALTIN",
  "pname": "NAIM",
  "surname": "CAKOLLI",
  "gender": "M",
  "class": "X9",
  "teacher": "Agim Tahiri"
 },
 {
  "name": "ANDI",
  "pname": "AGIM",
  "surname": "QERIMI",
  "gender": "M",
  "class": "X9",
  "teacher": "Agim Tahiri"
 },
 {
  "name": "Blend",
  "pname": "Agim",
  "surname": "Maloku",
  "gender": "M",
  "class": "X9",
  "teacher": "Agim Tahiri"
 },
 {
  "name": "Blerton ",
  "pname": "Shaban",
  "surname": "Ferati",
  "gender": "M",
  "class": "X9",
  "teacher": "Agim Tahiri"
 },
 {
  "name": "Drilon",
  "pname": "Nazim",
  "surname": "Dushica",
  "gender": "M",
  "class": "X9",
  "teacher": "Agim Tahiri"
 },
 {
  "name": "Drilon",
  "pname": "Skender",
  "surname": "Qehaja",
  "gender": "M",
  "class": "X9",
  "teacher": "Agim Tahiri"
 },
 {
  "name": "Luan",
  "pname": "Besnik",
  "surname": "Rashiti",
  "gender": "M",
  "class": "X9",
  "teacher": "Agim Tahiri"
 },
 {
  "name": "Mendush",
  "pname": "Ruzhdi",
  "surname": "Syla",
  "gender": "M",
  "class": "X9",
  "teacher": "Agim Tahiri"
 },
 {
  "name": "Mirlind",
  "pname": "Afrim",
  "surname": "Hajdini",
  "gender": "M",
  "class": "X9",
  "teacher": "Agim Tahiri"
 },
 {
  "name": "Shkodran",
  "pname": "Bashkim",
  "surname": "Musliu",
  "gender": "M",
  "class": "X9",
  "teacher": "Agim Tahiri"
 },
 {
  "name": "Sueda",
  "pname": "Ahmet",
  "surname": "Ismaili",
  "gender": "F",
  "class": "X9",
  "teacher": "Agim Tahiri"
 },
 {
  "name": "Endrit",
  "pname": "Hafiz",
  "surname": "Abazi",
  "class": "X9",
  "teacher": "Agim Tahiri"
 },
 {
  "name": "Eriona",
  "pname": "Ekrem",
  "surname": "Kovani",
  "class": "X9",
  "teacher": "Agim Tahiri"
 },
 {
  "name": "ARBENITA",
  "pname": "Islam",
  "surname": "SHALA",
  "gender": "F",
  "class": "X\/10",
  "teacher": "Mehmet Rapuca"
 },
 {
  "name": "ARDITA",
  "pname": "Fehmi",
  "surname": "SPAHIJA",
  "gender": "F",
  "class": "X\/10",
  "teacher": "Mehmet Rapuca"
 },
 {
  "name": "BLEONA",
  "pname": "Elsadat",
  "surname": "SELIMI",
  "gender": "F",
  "class": "X\/10",
  "teacher": "Mehmet Rapuca"
 },
 {
  "name": "DAFINA ",
  "pname": "FATMIR",
  "surname": "MUSHICA",
  "gender": "F",
  "class": "X\/10",
  "teacher": "Mehmet Rapuca"
 },
 {
  "name": "Eldonit",
  "pname": "Isuf",
  "surname": "Sahiti",
  "gender": "M",
  "class": "X\/10",
  "teacher": "Mehmet Rapuca"
 },
 {
  "name": "ERIONA",
  "pname": "XHEMAIL",
  "surname": "BUNJAKU",
  "gender": "F",
  "class": "X\/10",
  "teacher": "Mehmet Rapuca"
 },
 {
  "name": "Fitore",
  "pname": "Besim ",
  "surname": "Kastrati",
  "gender": "F",
  "class": "X\/10",
  "teacher": "Mehmet Rapuca"
 },
 {
  "name": "GENTIANA",
  "pname": "Islam",
  "surname": "SHALA",
  "gender": "F",
  "class": "X\/10",
  "teacher": "Mehmet Rapuca"
 },
 {
  "name": "FLORENTINA",
  "pname": "Zihadin",
  "surname": "KURTALANI",
  "gender": "F",
  "class": "X\/10",
  "teacher": "Mehmet Rapuca"
 },
 {
  "name": "Andi ",
  "pname": "Musli",
  "surname": "Ibrahimi",
  "gender": "M",
  "class": "XI\/1",
  "teacher": "Florim Bajrami"
 },
 {
  "name": "Arbis",
  "pname": "sejdi",
  "surname": "Ajeti",
  "gender": "M",
  "class": "XI\/1",
  "teacher": "Florim Bajrami"
 },
 {
  "name": "Aris ",
  "pname": "Ganimete",
  "surname": "Haliti",
  "gender": "M",
  "class": "XI\/1",
  "teacher": "Florim Bajrami"
 },
 {
  "name": "Artin ",
  "pname": "Skender",
  "surname": "Bajrami",
  "gender": "M",
  "class": "XI\/1",
  "teacher": "Florim Bajrami"
 },
 {
  "name": "Bledar",
  "pname": "Arianit",
  "surname": "Sherifi",
  "gender": "M",
  "class": "XI\/1",
  "teacher": "Florim Bajrami"
 },
 {
  "name": "Blerton ",
  "pname": "Isa",
  "surname": "Ahmeti",
  "gender": "M",
  "class": "XI\/1",
  "teacher": "Florim Bajrami"
 },
 {
  "name": "Edi ",
  "pname": "Burim",
  "surname": "Toska",
  "gender": "M",
  "class": "XI\/1",
  "teacher": "Florim Bajrami"
 },
 {
  "name": "Edonis",
  "pname": "Refik",
  "surname": "Bllaca",
  "gender": "M",
  "class": "XI\/1",
  "teacher": "Florim Bajrami"
 },
 {
  "name": "Engjell",
  "pname": "Sabri",
  "surname": "Jashari",
  "gender": "M",
  "class": "XI\/1",
  "teacher": "Florim Bajrami"
 },
 {
  "name": "Erit ",
  "pname": "Nexhat ",
  "surname": "Bajrami",
  "gender": "M",
  "class": "XI\/1",
  "teacher": "Florim Bajrami"
 },
 {
  "name": "Getuar",
  "pname": "Elmaz",
  "surname": "Orana",
  "gender": "M",
  "class": "XI\/1",
  "teacher": "Florim Bajrami"
 },
 {
  "name": "Leon",
  "pname": "Fatlum",
  "surname": "Agaj",
  "gender": "M",
  "class": "XI\/1",
  "teacher": "Florim Bajrami"
 },
 {
  "name": "Lorik",
  "pname": "Bujar",
  "surname": "Rexhepi",
  "gender": "M",
  "class": "XI\/1",
  "teacher": "Florim Bajrami"
 },
 {
  "name": "Omar ",
  "pname": "Shpend",
  "surname": "Aliu",
  "gender": "M",
  "class": "XI\/1",
  "teacher": "Florim Bajrami"
 },
 {
  "name": "Orges ",
  "pname": "Avni",
  "surname": "Cuci",
  "gender": "M",
  "class": "XI\/1",
  "teacher": "Florim Bajrami"
 },
 {
  "name": "Reshat ",
  "pname": "Nagip",
  "surname": "Omeri",
  "gender": "M",
  "class": "XI\/1",
  "teacher": "Florim Bajrami"
 },
 {
  "name": "Erion",
  "pname": "Selami",
  "surname": "Haziri",
  "gender": "M",
  "class": "XI\/1",
  "teacher": "Florim Bajrami"
 },
 {
  "name": "SHAIP ",
  "pname": "Agim",
  "surname": "Halili",
  "gender": "M",
  "class": "XI\/1",
  "teacher": "Florim Bajrami"
 },
 {
  "name": "Aridon ",
  "pname": "Muhamet",
  "surname": "Zylfiu",
  "gender": "M",
  "class": "XI\/2",
  "teacher": "Shqipe Aliu"
 },
 {
  "name": "Bujar",
  "pname": "Ilmi",
  "surname": "Isaku",
  "gender": "M",
  "class": "XI\/2",
  "teacher": "Shqipe Aliu"
 },
 {
  "name": "Donat ",
  "pname": "Arben",
  "surname": "Salihu",
  "gender": "M",
  "class": "XI\/2",
  "teacher": "Shqipe Aliu"
 },
 {
  "name": "Endri ",
  "pname": "Bekim",
  "surname": "Emini",
  "gender": "M",
  "class": "XI\/2",
  "teacher": "Shqipe Aliu"
 },
 {
  "name": "Endrit ",
  "pname": "Agmir",
  "surname": "Zejnullahu",
  "gender": "M",
  "class": "XI\/2",
  "teacher": "Shqipe Aliu"
 },
 {
  "name": "Elon ",
  "pname": "Lulzim",
  "surname": "Xhemaili",
  "gender": "M",
  "class": "XI\/2",
  "teacher": "Shqipe Aliu"
 },
 {
  "name": "Hevzi ",
  "pname": "Fatmir",
  "surname": "Zejnullahu",
  "gender": "M",
  "class": "XI\/2",
  "teacher": "Shqipe Aliu"
 },
 {
  "name": "Leontrit ",
  "pname": "Gjem",
  "surname": "Gërbovci",
  "gender": "M",
  "class": "XI\/2",
  "teacher": "Shqipe Aliu"
 },
 {
  "name": "Qemajl",
  "pname": "Bujar",
  "surname": "Kastrati",
  "gender": "M",
  "class": "XI\/2",
  "teacher": "Shqipe Aliu"
 },
 {
  "name": "Shaban ",
  "pname": "Afrim",
  "surname": "Limani",
  "gender": "M",
  "class": "XI\/2",
  "teacher": "Shqipe Aliu"
 },
 {
  "name": "Venis ",
  "pname": "Bekim",
  "surname": "Murati",
  "gender": "M",
  "class": "XI\/2",
  "teacher": "Shqipe Aliu"
 },
 {
  "name": "Yll ",
  "pname": "Bujar",
  "surname": "Rexhepi",
  "gender": "M",
  "class": "XI\/2",
  "teacher": "Shqipe Aliu"
 },
 {
  "name": "Ymer",
  "pname": "Ismajl",
  "surname": "Imeri",
  "gender": "M",
  "class": "XI\/2",
  "teacher": "Shqipe Aliu"
 },
 {
  "name": "Andi ",
  "pname": "Florim",
  "surname": "Aliji",
  "gender": "M",
  "class": "XI\/2",
  "teacher": "Shqipe Aliu"
 },
 {
  "name": "Anisë",
  "pname": "Zejnullah",
  "surname": "Ademi",
  "gender": "F",
  "class": "XI\/3",
  "teacher": "Lulzim Bajrami"
 },
 {
  "name": "Art",
  "pname": "Behlul",
  "surname": "Beluli",
  "gender": "M",
  "class": "XI\/3",
  "teacher": "Lulzim Bajrami"
 },
 {
  "name": "Bleart",
  "pname": "Ferat",
  "surname": "Shabani",
  "gender": "M",
  "class": "XI\/3",
  "teacher": "Lulzim Bajrami"
 },
 {
  "name": "Blend ",
  "pname": "Ymret",
  "surname": "Limani",
  "gender": "M",
  "class": "XI\/3",
  "teacher": "Lulzim Bajrami"
 },
 {
  "name": "Bleond",
  "pname": "Qahil",
  "surname": "Neziri",
  "gender": "M",
  "class": "XI\/3",
  "teacher": "Lulzim Bajrami"
 },
 {
  "name": "Eris ",
  "pname": "Bajram",
  "surname": "Uruqi",
  "gender": "M",
  "class": "XI\/3",
  "teacher": "Lulzim Bajrami"
 },
 {
  "name": "Leona",
  "pname": "Ruzhdi",
  "surname": "Selishta",
  "gender": "F",
  "class": "XI\/3",
  "teacher": "Lulzim Bajrami"
 },
 {
  "name": "Migjen ",
  "pname": "Adem",
  "surname": "Sylejmani",
  "gender": "M",
  "class": "XI\/3",
  "teacher": "Lulzim Bajrami"
 },
 {
  "name": "Erion ",
  "pname": "Sami",
  "surname": "Uruqi",
  "gender": "M",
  "class": "XI\/3",
  "teacher": "Lulzim Bajrami"
 },
 {
  "name": "Ardit",
  "pname": "Musah",
  "surname": "Ibrahimi",
  "gender": "M",
  "class": "XI\/4",
  "teacher": "Arbër Shabani"
 },
 {
  "name": "Viol",
  "pname": "Artan",
  "surname": "Shkodra",
  "gender": "M",
  "class": "XI\/4",
  "teacher": "Arbër Shabani"
 },
 {
  "name": "Duet ",
  "pname": "Xhelal",
  "surname": "Isufi",
  "gender": "M",
  "class": "XI\/4",
  "teacher": "Arbër Shabani"
 },
 {
  "name": "Yll",
  "pname": "Naser",
  "surname": "Dermaku",
  "gender": "M",
  "class": "XI\/4",
  "teacher": "Arbër Shabani"
 },
 {
  "name": "Eduard ",
  "pname": "Adem",
  "surname": "Dermaku",
  "gender": "M",
  "class": "XI\/4",
  "teacher": "Arbër Shabani"
 },
 {
  "name": "Valdrin ",
  "pname": "Xhevat",
  "surname": "Jahiri",
  "gender": "M",
  "class": "XI\/4",
  "teacher": "Arbër Shabani"
 },
 {
  "name": "Jeton ",
  "pname": "Maliq",
  "surname": "Zahiri",
  "gender": "M",
  "class": "XI\/4",
  "teacher": "Arbër Shabani"
 },
 {
  "name": "ALBINOT",
  "pname": "Murat",
  "surname": "DEMATI",
  "gender": "M",
  "class": "XI\/5",
  "teacher": "XHAFER XHELILI"
 },
 {
  "name": "ILMI",
  "pname": "Basri",
  "surname": "ABAZI",
  "gender": "M",
  "class": "XI\/5",
  "teacher": "XHAFER XHELILI"
 },
 {
  "name": "Ardit",
  "pname": "Arbena",
  "surname": "Gashi",
  "gender": "M",
  "class": "XI\/5",
  "teacher": "XHAFER XHELILI"
 },
 {
  "name": "ADRIATIK ",
  "surname": "Kurexhaj",
  "gender": "M",
  "class": "XI\/5",
  "teacher": "XHAFER XHELILI"
 },
 {
  "name": "MUSTAFE",
  "pname": "Muhamet",
  "surname": "RAMADANI",
  "gender": "M",
  "class": "XI\/5",
  "teacher": "XHAFER XHELILI"
 },
 {
  "name": "KLAUDIN",
  "pname": "Besnik",
  "surname": "SALIHU",
  "gender": "M",
  "class": "XI\/5",
  "teacher": "XHAFER XHELILI"
 },
 {
  "name": "RIGON ",
  "pname": "Agim",
  "surname": "VESELI",
  "gender": "M",
  "class": "XI\/5",
  "teacher": "XHAFER XHELILI"
 },
 {
  "name": "Anisa",
  "pname": "Xhafer",
  "surname": "Xhelili",
  "gender": "F",
  "class": "XI\/6",
  "teacher": "Burim Dërmaku"
 },
 {
  "name": "Albert",
  "pname": "Ismajl",
  "surname": "Kqiku",
  "gender": "M",
  "class": "XI\/6",
  "teacher": "Burim Dërmaku"
 },
 {
  "name": "Arbnor",
  "pname": "Enver",
  "surname": "Murseli",
  "gender": "M",
  "class": "XI\/6",
  "teacher": "Burim Dërmaku"
 },
 {
  "name": "Aulon ",
  "pname": "Faton",
  "surname": "Haziri",
  "gender": "M",
  "class": "XI\/6",
  "teacher": "Burim Dërmaku"
 },
 {
  "name": "Blerta ",
  "pname": "Bejtullah",
  "surname": "Sylejmani",
  "gender": "F",
  "class": "XI\/6",
  "teacher": "Burim Dërmaku"
 },
 {
  "name": "Edonisa ",
  "pname": "Shaban",
  "surname": "Zuzaku",
  "gender": "F",
  "class": "Xi\/6",
  "teacher": "Burim Dërmaku"
 },
 {
  "name": "Erijon ",
  "pname": "Nijazi",
  "surname": "Ibrahimi",
  "gender": "M",
  "class": "XI\/6",
  "teacher": "Burim Dërmaku"
 },
 {
  "name": "Florian ",
  "pname": "Fazli",
  "surname": "Kqiku",
  "gender": "M",
  "class": "XI\/6",
  "teacher": "Burim Dërmaku"
 },
 {
  "name": "Gresa ",
  "pname": "Burim",
  "surname": "Haliti",
  "gender": "F",
  "class": "XI\/6",
  "teacher": "Burim Dërmaku"
 },
 {
  "name": "Gresa ",
  "pname": "Kemajl",
  "surname": "Murtezi",
  "gender": "F",
  "class": "XI\/6",
  "teacher": "Burim Dërmaku"
 },
 {
  "name": "Leart ",
  "pname": "Enver",
  "surname": "Halabaku",
  "gender": "M",
  "class": "XI\/6",
  "teacher": "Burim Dërmaku"
 },
 {
  "name": "Paulin ",
  "pname": "Naim",
  "surname": "Leka",
  "gender": "M",
  "class": "XI\/6",
  "teacher": "Burim Dërmaku"
 },
 {
  "name": "Elmirë ",
  "pname": "Isuf",
  "surname": "Asllani",
  "gender": "F",
  "class": "XI\/7",
  "teacher": "BUJAR KURTESHI"
 },
 {
  "name": "Elona ",
  "pname": "Tefik",
  "surname": "Shkodra",
  "gender": "F",
  "class": "XI\/7",
  "teacher": "BUJAR KURTESHI"
 },
 {
  "name": "Elsa",
  "pname": "Rexhep",
  "surname": "Bajraliu",
  "gender": "F",
  "class": "XI\/7",
  "teacher": "BUJAR KURTESHI"
 },
 {
  "name": "Erion ",
  "pname": "Adem",
  "surname": "Ajvazi",
  "gender": "M",
  "class": "XI\/7",
  "teacher": "BUJAR KURTESHI"
 },
 {
  "name": "Liola",
  "pname": "Arsim",
  "surname": "Selishta",
  "gender": "F",
  "class": "XI\/7",
  "teacher": "BUJAR KURTESHI"
 },
 {
  "name": "Maliq",
  "pname": "Ismet",
  "surname": "Murtezi",
  "gender": "M",
  "class": "XI\/7",
  "teacher": "BUJAR KURTESHI"
 },
 {
  "name": "Rinis",
  "pname": "Sabit",
  "surname": "Demi",
  "gender": "M",
  "class": "XI\/7",
  "teacher": "BUJAR KURTESHI"
 },
 {
  "name": "Rinor",
  "pname": "Xhevat",
  "surname": "Neziri",
  "gender": "M",
  "class": "XI\/7",
  "teacher": "BUJAR KURTESHI"
 },
 {
  "name": "Endriti",
  "pname": "Besim",
  "surname": " Xhymshit",
  "gender": "M",
  "class": "XI\/8",
  "teacher": "Zenun Ukshini"
 },
 {
  "name": "Gentrit ",
  "pname": "Sahit",
  "surname": "Idrizi",
  "gender": "M",
  "class": "XI\/8",
  "teacher": "Zenun Ukshini"
 },
 {
  "name": "Leon",
  "pname": "Fehmi",
  "surname": "Sylejmani",
  "gender": "M",
  "class": "XI\/8",
  "teacher": "Zenun Ukshini"
 },
 {
  "name": "Luan",
  "pname": "Liman",
  "surname": "Limani",
  "gender": "M",
  "class": "XI\/8",
  "teacher": "Zenun Ukshini"
 },
 {
  "name": "ADI",
  "pname": "Rahim",
  "surname": "MUSLIU",
  "gender": "M",
  "class": "XI\/9",
  "teacher": "ARTON MEHMETI"
 },
 {
  "name": "ALTIN ",
  "pname": "Liman",
  "surname": "JAHIU",
  "gender": "M",
  "class": "XI\/9",
  "teacher": "ARTON MEHMETI"
 },
 {
  "name": "ALTRIM ",
  "pname": "Sylejman",
  "surname": "SYLEJMANI",
  "gender": "M",
  "class": "XI\/9",
  "teacher": "ARTON MEHMETI"
 },
 {
  "name": "Arian",
  "pname": "Ekrem",
  "surname": "BYQMETI",
  "gender": "M",
  "class": "XI\/9",
  "teacher": "ARTON MEHMETI"
 },
 {
  "name": "ART ",
  "pname": "Ragip",
  "surname": "RAMIZI",
  "gender": "M",
  "class": "XI\/9",
  "teacher": "ARTON MEHMETI"
 },
 {
  "name": "BLERON ",
  "pname": "Ruzhdi",
  "surname": "SADRIU",
  "gender": "M",
  "class": "XI\/9",
  "teacher": "ARTON MEHMETI"
 },
 {
  "name": "EDISON ",
  "pname": "Burim",
  "surname": "HAJDARI",
  "gender": "M",
  "class": "XI\/9",
  "teacher": "ARTON MEHMETI"
 },
 {
  "name": "EDISON ",
  "pname": "Miredita",
  "surname": "Momqilla",
  "gender": "M",
  "class": "XI\/9",
  "teacher": "ARTON MEHMETI"
 },
 {
  "name": "ELVIS ",
  "pname": "Ekrem",
  "surname": "RASHITI",
  "gender": "M",
  "class": "XI\/9",
  "teacher": "ARTON MEHMETI"
 },
 {
  "name": "ERALD",
  "pname": "Ruzhdi",
  "surname": "DEMOLLI",
  "gender": "M",
  "class": "XI\/9",
  "teacher": "ARTON MEHMETI"
 },
 {
  "name": "HAMDI ",
  "pname": "Rexhep",
  "surname": "AJETI",
  "gender": "M",
  "class": "XI\/9",
  "teacher": "ARTON MEHMETI"
 },
 {
  "name": "IBRAHIM ",
  "pname": "Zijadin",
  "surname": "MAROVCA",
  "gender": "M",
  "class": "XI\/9",
  "teacher": "ARTON MEHMETI"
 },
 {
  "name": "JETSIM",
  "pname": "Afrim",
  "surname": "LIMANI",
  "gender": "M",
  "class": "XI\/9",
  "teacher": "ARTON MEHMETI"
 },
 {
  "name": "LEON ",
  "pname": "Avdi",
  "surname": "MALIQI",
  "gender": "M",
  "class": "XI\/9",
  "teacher": "ARTON MEHMETI"
 },
 {
  "name": "Shaip ",
  "pname": "Vehbi",
  "surname": "Maliqi",
  "gender": "M",
  "class": "XI\/9",
  "teacher": "ARTON MEHMETI"
 },
 {
  "name": "LEONIS",
  "surname": "BUNJAKU",
  "gender": "M",
  "class": "XI\/9",
  "teacher": "ARTON MEHMETI"
 },
 {
  "name": "Albert",
  "pname": "Sefer",
  "surname": "Momqilla",
  "gender": "M",
  "class": "XI\/10",
  "teacher": "Xhevdet Agaj"
 },
 {
  "name": "Albi",
  "pname": "Nexhat ",
  "surname": "Sylejmani",
  "gender": "M",
  "class": "XI\/10",
  "teacher": "Xhevdet Agaj"
 },
 {
  "name": "Dren ",
  "pname": "Hajrush",
  "surname": "Ahmeti",
  "gender": "M",
  "class": "XI\/10",
  "teacher": "Xhevdet Agaj"
 },
 {
  "name": "Ensar",
  "pname": "Lulzim",
  "surname": "Rrudhani",
  "gender": "M",
  "class": "XI\/10",
  "teacher": "Xhevdet Agaj"
 },
 {
  "name": "Fetah",
  "pname": "Agim",
  "surname": "Dërmaku",
  "gender": "M",
  "class": "XI\/10",
  "teacher": "Xhevdet Agaj"
 },
 {
  "name": "Gentrit",
  "pname": "Hysen",
  "surname": "Kqiku",
  "gender": "M",
  "class": "XI\/10",
  "teacher": "Xhevdet Agaj"
 },
 {
  "name": "Laurand ",
  "pname": "Beqir",
  "surname": "Zeqiri",
  "gender": "M",
  "class": "XI\/10",
  "teacher": "Xhevdet Agaj"
 },
 {
  "name": "Lirim ",
  "pname": "Skender",
  "surname": "Sherifi",
  "gender": "M",
  "class": "XI\/10",
  "teacher": "Xhevdet Agaj"
 },
 {
  "name": "Qamil ",
  "pname": "Bekim",
  "surname": "Ajeti",
  "gender": "M",
  "class": "XI\/10",
  "teacher": "Xhevdet Agaj"
 },
 {
  "name": "Ukshin",
  "pname": "Nazim",
  "surname": "Lipovica",
  "gender": "M",
  "class": "XI\/10",
  "teacher": "Xhevdet Agaj"
 },
 {
  "name": "Visar",
  "pname": "Feim",
  "surname": "Selishta",
  "gender": "M",
  "class": "XI\/10",
  "teacher": "Xhevdet Agaj"
 },
 {
  "name": "Erton ",
  "pname": "Hajriz",
  "surname": "Ukshini",
  "gender": "M",
  "class": "XI\/10",
  "teacher": "Xhevdet Agaj"
 },
 {
  "name": "ART ",
  "pname": "Nexhmedin",
  "surname": "RUSHITI",
  "gender": "M",
  "class": "XI\/11",
  "teacher": "SEFER KASTRATI"
 },
 {
  "name": "Altina ",
  "pname": "Adem",
  "surname": "Sylejmani",
  "gender": "M",
  "class": "XI\/11",
  "teacher": "SEFER KASTRATI"
 },
 {
  "name": "BARDH ",
  "pname": "Skender",
  "surname": "OSMANI",
  "gender": "M",
  "class": "XI\/11",
  "teacher": "SEFER KASTRATI"
 },
 {
  "name": "BLENDIONE",
  "pname": "Kadri",
  "surname": "MUSTAFA",
  "gender": "F",
  "class": "XI\/11",
  "teacher": "SEFER KASTRATI"
 },
 {
  "name": "BLERTIN ",
  "pname": "Selver",
  "surname": "ZYMERI",
  "gender": "M",
  "class": "XI\/11",
  "teacher": "SEFER KASTRATI"
 },
 {
  "name": "ILAZ",
  "pname": "Raif",
  "surname": "GAGICA",
  "gender": "M",
  "class": "XI\/11",
  "teacher": "SEFER KASTRATI"
 },
 {
  "name": "Arlind",
  "pname": "Nexhat ",
  "surname": "Basha",
  "gender": "M",
  "class": "XI\/11",
  "teacher": "SEFER KASTRATI"
 },
 {
  "name": "VALDET ",
  "pname": "Xhevdet",
  "surname": "QAILI",
  "gender": "M",
  "class": "XI\/11",
  "teacher": "SEFER KASTRATI"
 },
 {
  "name": "Engjell ",
  "pname": "Flamur ",
  "surname": "Dalipi",
  "gender": "M",
  "class": "XI\/12",
  "teacher": "Hata Shkodra "
 },
 {
  "name": "Flakron",
  "pname": "Naser",
  "surname": "Hajdini",
  "gender": "M",
  "class": "XI\/12",
  "teacher": "Hata Shkodra "
 },
 {
  "name": "Festina ",
  "pname": "Zijadin",
  "surname": "Kurtalani",
  "gender": "F",
  "class": "XI\/12",
  "teacher": "Hata Shkodra "
 },
 {
  "name": "Luan",
  "pname": "Senat",
  "surname": "Regjepi",
  "gender": "M",
  "class": "XI\/12",
  "teacher": "Hata Shkodra "
 },
 {
  "name": "Kastriot",
  "pname": "Maksut",
  "surname": "Alishani",
  "gender": "M",
  "class": "XI\/12",
  "teacher": "Hata Shkodra "
 },
 {
  "name": "Makfire",
  "pname": "Rexhep",
  "surname": "Hafizi",
  "gender": "F",
  "class": "XI\/12",
  "teacher": "Hata Shkodra "
 },
 {
  "name": "Shpetim",
  "pname": "Sedat",
  "surname": "Arifi",
  "gender": "M",
  "class": "XI\/12",
  "teacher": "Hata Shkodra "
 }
]